torch_tensorrt_bzl-1.3.0.dist-info/METADATA
torch_tensorrt_bzl-1.3.0.dist-info/top_level.txt
torch_tensorrt_bzl-1.3.0.dist-info/WHEEL
torch_tensorrt_bzl-1.3.0.dist-info/LICENSE
torch_tensorrt_bzl-1.3.0.dist-info/RECORD
torch_tensorrt.libs/libcudart-e409450e.so.11.7.60
torch_tensorrt/ptq.py
torch_tensorrt/_TRTModuleNext.py
torch_tensorrt/_compile.py
torch_tensorrt/_version.py
torch_tensorrt/logging.py
torch_tensorrt/_Input.py
torch_tensorrt/_Device.py
torch_tensorrt/__init__.py
torch_tensorrt/_enums.py
torch_tensorrt/_util.py
torch_tensorrt/_C.cpython-39-x86_64-linux-gnu.so
torch_tensorrt/fx/trt_module.py
torch_tensorrt/fx/__init__.py
torch_tensorrt/fx/fx2trt.py
torch_tensorrt/fx/input_tensor_spec.py
torch_tensorrt/fx/types.py
torch_tensorrt/fx/utils.py
torch_tensorrt/fx/converter_registry.py
torch_tensorrt/fx/lower.py
torch_tensorrt/fx/lower_setting.py
torch_tensorrt/fx/diagnostics.py
torch_tensorrt/fx/observer.py
torch_tensorrt/fx/tools/trt_profiler_sorted.py
torch_tensorrt/fx/tools/timing_cache_utils.py
torch_tensorrt/fx/tools/common_fx2trt.py
torch_tensorrt/fx/tools/graph_util.py
torch_tensorrt/fx/tools/tensor_prop.py
torch_tensorrt/fx/tools/trt_splitter.py
torch_tensorrt/fx/tools/trt_minimizer.py
torch_tensorrt/fx/tools/__init__.py
torch_tensorrt/fx/tools/model_packager.py
torch_tensorrt/fx/tools/engine_layer_visualize.py
torch_tensorrt/fx/tools/node_profiler.py
torch_tensorrt/fx/tracer/__init__.py
torch_tensorrt/fx/tracer/dispatch_tracer/__init__.py
torch_tensorrt/fx/tracer/dispatch_tracer/tracer.py
torch_tensorrt/fx/tracer/acc_tracer/acc_shape_prop.py
torch_tensorrt/fx/tracer/acc_tracer/acc_utils.py
torch_tensorrt/fx/tracer/acc_tracer/__init__.py
torch_tensorrt/fx/tracer/acc_tracer/acc_ops.py
torch_tensorrt/fx/tracer/acc_tracer/acc_op_properties.py
torch_tensorrt/fx/tracer/acc_tracer/acc_normalizer.py
torch_tensorrt/fx/tracer/acc_tracer/acc_tracer.py
torch_tensorrt/fx/passes/lower_basic_pass.py
torch_tensorrt/fx/passes/lower_pass_manager_builder.py
torch_tensorrt/fx/passes/__init__.py
torch_tensorrt/fx/passes/pass_utils.py
torch_tensorrt/fx/passes/graph_opts.py
torch_tensorrt/fx/passes/remove_duplicate_output_args.py
