Metadata-Version: 2.1
Name: torch-tensorrt-bzl
Version: 1.3.0
Summary: Torch-TensorRT is a package which allows users to automatically compile PyTorch and TorchScript modules to TensorRT while remaining in PyTorch
Home-page: https://nvidia.github.io/torch-tensorrt
Author: NVIDIA
Author-email: narens@nvidia.com
License: BSD
Platform: UNKNOWN
Classifier: Development Status :: 5 - Production/Stable
Classifier: Environment :: GPU :: NVIDIA CUDA
Classifier: License :: OSI Approved :: BSD License
Classifier: Intended Audience :: Developers
Classifier: Intended Audience :: Science/Research
Classifier: Operating System :: POSIX :: Linux
Classifier: Programming Language :: C++
Classifier: Programming Language :: Python
Classifier: Programming Language :: Python :: Implementation :: CPython
Classifier: Topic :: Scientific/Engineering
Classifier: Topic :: Scientific/Engineering :: Artificial Intelligence
Classifier: Topic :: Software Development
Classifier: Topic :: Software Development :: Libraries
Requires-Python: >=3.7
Requires-Dist: torch (<1.14.0,>=1.13.0)
Requires-Dist: tensorrt (<8.6.0,>=8.5.1.7)
